convertus_alexanastgr/__init__.py
convertus_alexanastgr/convertus.py
convertus_alexanastgr-0.0.1.dist-info/METADATA
convertus_alexanastgr-0.0.1.dist-info/WHEEL
convertus_alexanastgr-0.0.1.dist-info/licenses/LICENSE
convertus_alexanastgr-0.0.1.dist-info/RECORD
