Metadata-Version: 2.1
Name: convertus_alexanastgr
Version: 0.0.1
Summary: A small package that convert images on a directory
Project-URL: Homepage, https://github.com/pypa/sampleproject
Project-URL: Bug Tracker, https://github.com/pypa/sampleproject/issues
Author-email: Alexandros Anastasiadis <alexanastasgr@gmail.com>
License-File: LICENSE
Classifier: License :: OSI Approved :: MIT License
Classifier: Operating System :: OS Independent
Classifier: Programming Language :: Python :: 3
Requires-Python: >=3.7
